xbTools/__init__.py
xbTools/par.json
xbTools/xbeachpost.py
xbTools/xbeachtools.py
xbTools/general/__init__.py
xbTools/general/deg2uv.py
xbTools/general/executing_runs.py
xbTools/general/geometry.py
xbTools/general/visualize_mesh.py
xbTools/general/wave_functions.py
xbTools/grid/__init__.py
xbTools/grid/creation.py
xbTools/grid/extension.py
xbTools/grid/grid_check.py
xbTools/grid/refinement.py
xbTools-1.0.2.dist-info/LICENSE
xbTools-1.0.2.dist-info/METADATA
xbTools-1.0.2.dist-info/WHEEL
xbTools-1.0.2.dist-info/top_level.txt
xbTools-1.0.2.dist-info/RECORD
