Metadata-Version: 2.1
Name: xbTools
Version: 1.0.2
Summary: Toolbox to analyse and setup xbeach models
Home-page: https://github.com/openearth/xbeach-toolbox
Author: Menno de Ridder
Author-email: menno.deridder@deltares.nl
License: GNU General Public License v3.0
Requires-Python: >=3, <4
License-File: LICENSE
Requires-Dist: numpy
Requires-Dist: matplotlib >=3.5.0
Requires-Dist: netCDF4 >=1.6.0
Requires-Dist: scipy >=1.10.0
Requires-Dist: datetime
Requires-Dist: geopandas >=0.13.0
Requires-Dist: shapely >=2.0.0
Requires-Dist: fiona >=1.9.4.post1
Requires-Dist: pytest
